VolorSavanna.py
__init__.py
clear.py
volorsavanna-0.0.20.dist-info/METADATA
volorsavanna-0.0.20.dist-info/WHEEL
volorsavanna-0.0.20.dist-info/top_level.txt
volorsavanna-0.0.20.dist-info/RECORD
