Metadata-Version: 2.4
Name: VolorSavanna
Version: 0.0.20
Summary: Volor Savanna is a text adventure game! To play: python3 -m VolorSavanna
Author: Invizabel
Project-URL: Homepage, https://github.com/Invizabel/Volor-Savanna
Project-URL: Bug Tracker, https://github.com/Invizabel/Volor-Savanna/issues
Classifier: Programming Language :: Python :: 3
Classifier: License :: OSI Approved :: MIT License
Classifier: Operating System :: OS Independent
Requires-Python: >=3.7
